{
  "font": {
    "name": "mangal.ttf",
    "size": 32,
    "color": "#3C0000"
  },
  "fields": {
    "name":        { "x": 300, "y": 650 },
    "birthDate":  { "x": 300, "y": 698 },
    "birthPlace": { "x": 300, "y": 746 },
    "birthTime":  { "x": 300, "y": 794 },
    "religion":   { "x": 300, "y": 842 },
    "caste":      { "x": 300, "y": 890 },
    "height":     { "x": 300, "y": 938 },
    "education":  { "x": 300, "y": 986 },
    "address":    { "x": 300, "y": 1034 },
    "mobile":     { "x": 300, "y": 1082 }
  }
}
